dave_reporting/__init__.cp312-win_amd64.pyd
dave_reporting/colors.cp312-win_amd64.pyd
dave_reporting/example_run_gui.cp312-win_amd64.pyd
dave_reporting/gui/__init__.cp312-win_amd64.pyd
dave_reporting/gui/basic_sections.cp312-win_amd64.pyd
dave_reporting/gui/common.cp312-win_amd64.pyd
dave_reporting/gui/docks.cp312-win_amd64.pyd
dave_reporting/gui/forms/__init__.cp312-win_amd64.pyd
dave_reporting/gui/forms/dock_report.cp312-win_amd64.pyd
dave_reporting/gui/forms/section_carene.cp312-win_amd64.pyd
dave_reporting/gui/forms/section_chapter.cp312-win_amd64.pyd
dave_reporting/gui/forms/section_lsm.cp312-win_amd64.pyd
dave_reporting/gui/forms/section_node.cp312-win_amd64.pyd
dave_reporting/gui/forms/section_nodes_table.cp312-win_amd64.pyd
dave_reporting/gui/forms/section_single_node.cp312-win_amd64.pyd
dave_reporting/gui/forms/section_tags.cp312-win_amd64.pyd
dave_reporting/gui/forms/section_text.cp312-win_amd64.pyd
dave_reporting/gui/forms/section_timestep.cp312-win_amd64.pyd
dave_reporting/gui/forms/section_viewportimage.cp312-win_amd64.pyd
dave_reporting/helpers/__init__.cp312-win_amd64.pyd
dave_reporting/helpers/feedback_and_terminate_dummies.cp312-win_amd64.pyd
dave_reporting/helpers/format_mpl_plot.cp312-win_amd64.pyd
dave_reporting/report/PDF_report.cp312-win_amd64.pyd
dave_reporting/report/__init__.cp312-win_amd64.pyd
dave_reporting/report/basic_sections.cp312-win_amd64.pyd
dave_reporting/report/common.cp312-win_amd64.pyd
dave_reporting/report/report.cp312-win_amd64.pyd
dave_reporting/report/timeline_loadcases.cp312-win_amd64.pyd
dave_reporting/report/timeline_sections.cp312-win_amd64.pyd
dave_reporting/report_resources/DAVE.svg
dave_reporting/report_resources/dave_logo_footer.png
dave_reporting/report_resources/carlito-main/.gitignore
dave_reporting/report_resources/carlito-main/AUTHORS.txt
dave_reporting/report_resources/carlito-main/OFL.txt
dave_reporting/report_resources/carlito-main/README.md
dave_reporting-2025.0.8.dist-info/licenses/LICENSE.txt
dave_reporting-2025.0.8.dist-info/METADATA
dave_reporting-2025.0.8.dist-info/WHEEL
dave_reporting-2025.0.8.dist-info/top_level.txt
dave_reporting-2025.0.8.dist-info/RECORD
